yaozarrs/__init__.py
yaozarrs/_axis.py
yaozarrs/_base.py
yaozarrs/_cli.py
yaozarrs/_demo_data.py
yaozarrs/_dim_spec.py
yaozarrs/_io.py
yaozarrs/_omero.py
yaozarrs/_storage.py
yaozarrs/_types.py
yaozarrs/_validate.py
yaozarrs/_validation_warning.py
yaozarrs/_zarr.py
yaozarrs/py.typed
yaozarrs/v04/__init__.py
yaozarrs/v04/_bf2raw.py
yaozarrs/v04/_image.py
yaozarrs/v04/_labels.py
yaozarrs/v04/_plate.py
yaozarrs/v04/_storage.py
yaozarrs/v04/_zarr_json.py
yaozarrs/v05/__init__.py
yaozarrs/v05/_bf2raw.py
yaozarrs/v05/_image.py
yaozarrs/v05/_labels.py
yaozarrs/v05/_plate.py
yaozarrs/v05/_storage.py
yaozarrs/v05/_zarr_json.py
yaozarrs/write/__init__.py
yaozarrs/write/v05/__init__.py
yaozarrs/write/v05/_write.py
yaozarrs-0.2.0.dist-info/METADATA
yaozarrs-0.2.0.dist-info/WHEEL
yaozarrs-0.2.0.dist-info/entry_points.txt
yaozarrs-0.2.0.dist-info/licenses/LICENSE
yaozarrs-0.2.0.dist-info/RECORD
