Metadata-Version: 2.4
Name: yaozarrs
Version: 0.2.0
Summary: Yet another ome-zarr model.
Project-URL: homepage, https://github.com/tlambert03/yaozarrs
Project-URL: repository, https://github.com/tlambert03/yaozarrs
Author-email: Talley Lambert <talley.lambert@gmail.com>
License: BSD-3-Clause
License-File: LICENSE
Classifier: Development Status :: 3 - Alpha
Classifier: License :: OSI Approved :: BSD License
Classifier: Programming Language :: Python :: 3
Classifier: Programming Language :: Python :: 3.10
Classifier: Programming Language :: Python :: 3.11
Classifier: Programming Language :: Python :: 3.12
Classifier: Programming Language :: Python :: 3.13
Classifier: Typing :: Typed
Requires-Python: >=3.10
Requires-Dist: pydantic-core>=2.20.0; python_version >= '3.13'
Requires-Dist: pydantic-core>=2.35.0; python_version >= '3.14'
Requires-Dist: pydantic>=2.5.0
Requires-Dist: typing-extensions>=4.6.0
Provides-Extra: io
Requires-Dist: fsspec[http,s3]>=2025.0; extra == 'io'
Provides-Extra: storage
Requires-Dist: fsspec[http,s3]>=2025.0; extra == 'storage'
Requires-Dist: zarr>=2.18; extra == 'storage'
Requires-Dist: zarr>=3.1.0; (python_version >= '3.11') and extra == 'storage'
Provides-Extra: write-tensorstore
Requires-Dist: tensorstore>=0.1.66; extra == 'write-tensorstore'
Requires-Dist: tensorstore>=0.1.71; (python_version >= '3.13') and extra == 'write-tensorstore'
Provides-Extra: write-zarr
Requires-Dist: zarr>=2.18; extra == 'write-zarr'
Requires-Dist: zarr>=3.1.0; (python_version >= '3.11') and extra == 'write-zarr'
Provides-Extra: write-zarrs
Requires-Dist: zarrs>=0.1.5; (python_version >= '3.11') and extra == 'write-zarrs'
